[
  {
    "ids": [ 6618 ],
    "guaranteed": [
      { "id": 526, "min": 1, "max": 1 }   //Bones
    ],
    "tables": [
      {
        "name": "Pre-roll",
        "weight": 8,
        "items": [
          { "id": 11929, "min": 1, "max": 1, "weight": 391 },   //Odium shard 2
          { "id": 11932, "min": 1, "max": 1, "weight": 391 }   //Malediction shard 2
        ]
      },
      {
        "name": "Weapons and armour",
        "weight": 165,
        "items": [
          { "id": 1731, "min": 1, "max": 1, "weight": 5470 },   //Amulet of power
          { "id": 9185, "min": 2, "max": 2, "weight": 3910 },   //Rune crossbow
          { "id": 2501, "min": 1, "max": 1, "weight": 3130 },   //Red d'hide body
          { "id": 868, "min": 10, "max": 10, "weight": 3130 }   //Rune knife
        ]
      },
      {
        "name": "Runes and ammunition",
        "weight": 74,
        "items": [
          { "id": 4698, "min": 30, "max": 30, "weight": 3130 },   //Mud rune
          { "id": 2, "min": 150, "max": 150, "weight": 3130 },   //Cannonball
          { "id": 11212, "min": 75, "max": 75, "weight": 781 }   //Dragon arrow
        ]
      },
      {
        "name": "Consumables",
        "weight": 231,
        "items": [
          { "id": 385, "min": 1, "max": 1, "weight": 6250 },   //Shark
          { "id": 6705, "min": 3, "max": 3, "weight": 6250 },   //Potato with cheese
          { "id": 2434, "min": 1, "max": 1, "weight": 6250 },   //Prayer potion(4)
          { "id": 2298, "min": 8, "max": 8, "weight": 3130 }   //Anchovy pizza (noted)
        ]
      },
      {
        "name": "Other",
        "weight": 520,
        "items": [
          { "id": 995, "min": 499, "max": 3998, "weight": 14099 },   //Coins
          { "id": 218, "min": 4, "max": 4, "weight": 6250 },   //Grimy dwarf weed (noted)
          { "id": 240, "min": 10, "max": 10, "weight": 4690 },   //White berries (noted)
          { "id": 443, "min": 40, "max": 40, "weight": 4690 },   //Silver ore (noted)
          { "id": 1622, "min": 6, "max": 6, "weight": 3910 },   //Uncut emerald (noted)
          { "id": 1750, "min": 10, "max": 10, "weight": 3910 },   //Red dragonhide (noted)
          { "id": 686, "min": 1, "max": 1, "weight": 3130 },   //Rusty sword
          { "id": 991, "min": 1, "max": 1, "weight": 3130 },   //Muddy key
          { "id": 9194, "min": 12, "max": 12, "weight": 3130 },   //Onyx bolt tips
          { "id": 10976, "min": 1, "max": 1, "weight": 1560 },   //Long bone
          { "id": 11990, "min": 1, "max": 1, "weight": 781 }   //Fedora
        ]
      },
      {
        "name": "Tertiary",
        "weight": 8,
        "items": [
          { "id": 2722, "min": 1, "max": 1, "weight": 781 }   //Clue scroll (hard)
        ]
      }
    ]
  }
]