[
  {
    "ids": [ 648, 649, 650, 651, 652, 653, 654, 698, 699, 700, 701, 702, 703, 704, 705 ],
    "guaranteed": [
      { "id": 532, "min": 1, "max": 1 }   //Big bones
    ],
    "tables": [
      {
        "name": "Weapons and armour",
        "weight": 134,
        "items": [
          { "id": 1199, "min": 1, "max": 1, "weight": 6250 },   //Adamant kiteshield
          { "id": 1125, "min": 1, "max": 1, "weight": 3130 },   //Black platebody
          { "id": 1357, "min": 1, "max": 1, "weight": 1560 },   //Adamant axe
          { "id": 1341, "min": 1, "max": 1, "weight": 781 },   //Black warhammer
          { "id": 1121, "min": 1, "max": 1, "weight": 781 },   //Mithril platebody
          { "id": 1373, "min": 1, "max": 1, "weight": 781 }   //Rune battleaxe
        ]
      },
      {
        "name": "Runes",
        "weight": 142,
        "items": [
          { "id": 565, "min": 2, "max": 2, "weight": 6250 },   //Blood rune
          { "id": 565, "min": 5, "max": 5, "weight": 3910 },   //Blood rune
          { "id": 563, "min": 4, "max": 4, "weight": 2339 },   //Law rune
          { "id": 560, "min": 15, "max": 15, "weight": 781 },   //Death rune
          { "id": 555, "min": 65, "max": 65, "weight": 781 }   //Water rune
        ]
      },
      {
        "name": "herb drop",
        "weight": 142,
        "items": [
          { "id": 0, "min": 1, "max": 1, "weight": 5 }
        ]
      },
      {
        "name": "Coins",
        "weight": 539,
        "items": [
          { "id": 995, "min": 30, "max": 30, "weight": 22699 },   //Coins
          { "id": 995, "min": 136, "max": 136, "weight": 19500 },   //Coins
          { "id": 995, "min": 200, "max": 200, "weight": 7810 },   //Coins
          { "id": 995, "min": 20, "max": 20, "weight": 3130 }   //Coins
        ]
      },
      {
        "name": "Other",
        "weight": 39,
        "items": [
          { "id": 380, "min": 6, "max": 6, "weight": 2339 },   //Lobster (noted)
          { "id": 359, "min": 4, "max": 4, "weight": 1560 }   //Raw tuna
        ]
      },
      {
        "name": "Tertiary",
        "weight": 53,
        "items": [
          { "id": 13484, "min": 1, "max": 1, "weight": 5000 },   //Ensouled troll head
          { "id": 10976, "min": 1, "max": 1, "weight": 250 },   //Long bone
          { "id": 10977, "min": 1, "max": 1, "weight": 20 }   //Curved bone
        ]
      }
    ]
  }
]