[
  {
    "ids": [ 3140, 4813, 7586 ],
    "tables": [
      {
        "name": "Runes",
        "weight": 384,
        "items": [
          { "id": 556, "min": 1, "max": 5, "weight": 781 },   //Air rune
          { "id": 555, "min": 1, "max": 5, "weight": 3130 }   //Water rune
        ]
      },
      {
        "name": "Other",
        "weight": 615,
        "items": [
          { "id": 995, "min": 1, "max": 30, "weight": 3130 },   //Coins
          { "id": 995, "min": 1, "max": 20, "weight": 3130 }   //Coins
        ]
      },
      {
        "name": "Tertiary",
        "weight": 76,
        "items": [
          { "id": 2677, "min": 1, "max": 1, "weight": 781 }   //Clue scroll (easy)
        ]
      }
    ]
  }
]